podler/__init__.py
podler/app.py
podler/downloader.py
podler-0.2.1.dist-info/entry_points.txt
podler-0.2.1.dist-info/WHEEL
podler-0.2.1.dist-info/METADATA
podler-0.2.1.dist-info/RECORD
