Metadata-Version: 2.1
Name: podler
Version: 0.2.1
Summary: podcast downloader
License: MIT
Author: Leo
Author-email: leetschau@gmail.com
Requires-Python: >=3.8,<4.0
Classifier: License :: OSI Approved :: MIT License
Classifier: Programming Language :: Python :: 3
Classifier: Programming Language :: Python :: 3.10
Classifier: Programming Language :: Python :: 3.8
Classifier: Programming Language :: Python :: 3.9
Requires-Dist: feedparser (>=6.0.8,<7.0.0)
Requires-Dist: fire (>=0.4.0,<0.5.0)
Requires-Dist: strictyaml (>=1.6.1,<2.0.0)
